Metadata-Version: 2.1
Name: mpqfractions
Version: 0.1
Summary: Drop-in replacement for fractions.Fraction, using gmpy
Home-page: https://github.com/gesellkammer/mpqfractions
Author: Eduardo Moguillansky
Author-email: eduardo.moguillansky@gmail.com
License: UNKNOWN
Platform: UNKNOWN
